satctl/__init__.py
satctl/cli.py
satctl/composites.py
satctl/config.py
satctl/model.py
satctl/py.typed
satctl/registry.py
satctl/utils.py
satctl/_config_data/satpy/composites/modis.yaml
satctl/_config_data/satpy/composites/msi.yaml
satctl/_config_data/satpy/composites/olci.yaml
satctl/_config_data/satpy/composites/sar-c.yaml
satctl/_config_data/satpy/composites/sen2_msi.yaml
satctl/_config_data/satpy/composites/slstr.yaml
satctl/_config_data/satpy/composites/viirs.yaml
satctl/_config_data/satpy/readers/sar-c_safe.yaml
satctl/_config_data/satpy/readers/slstr_l1b_rev4.yaml
satctl/auth/__init__.py
satctl/auth/base.py
satctl/auth/earthdata.py
satctl/auth/eumetsat.py
satctl/auth/odata.py
satctl/auth/s3.py
satctl/downloaders/__init__.py
satctl/downloaders/base.py
satctl/downloaders/http.py
satctl/downloaders/s3.py
satctl/progress/__init__.py
satctl/progress/base.py
satctl/progress/rich.py
satctl/progress/simple.py
satctl/progress/events/__init__.py
satctl/progress/events/bus.py
satctl/sources/__init__.py
satctl/sources/base.py
satctl/sources/earthdata.py
satctl/sources/modis.py
satctl/sources/mtg.py
satctl/sources/sentinel1.py
satctl/sources/sentinel2.py
satctl/sources/sentinel3.py
satctl/sources/viirs.py
satctl/writers/__init__.py
satctl/writers/base.py
satctl/writers/geotiff.py
satctl-0.3.4.dist-info/METADATA
satctl-0.3.4.dist-info/WHEEL
satctl-0.3.4.dist-info/entry_points.txt
satctl-0.3.4.dist-info/licenses/LICENSE
satctl-0.3.4.dist-info/RECORD
