Metadata-Version: 2.4
Name: satctl
Version: 0.3.4
Summary: Toolkit to search, download and process Earth Observation data
Author-email: Edoardo Arnaudo <edoardo.arnaudo@linksfoundation.com>, Luca Barco <andrea.bragagnolo@linksfoundation.com>, Andrea Bragagnolo <luca.barco@linksfoundation.com>, Gaetano Chiriaco <gaetano.chiriaco@linksfoundation.com>
License-File: LICENSE
Classifier: Development Status :: 3 - Alpha
Classifier: Intended Audience :: Developers
Classifier: Intended Audience :: Science/Research
Classifier: Operating System :: OS Independent
Classifier: Programming Language :: Python
Classifier: Programming Language :: Python :: 3
Classifier: Programming Language :: Python :: 3 :: Only
Classifier: Programming Language :: Python :: 3.10
Classifier: Programming Language :: Python :: 3.11
Classifier: Programming Language :: Python :: 3.12
Classifier: Programming Language :: Python :: 3.13
Classifier: Topic :: Scientific/Engineering :: GIS
Classifier: Topic :: Software Development :: Libraries
Requires-Python: >=3.10
Requires-Dist: boto3>=1.28.0
Requires-Dist: bottleneck>=1.6.0
Requires-Dist: earthaccess>=0.14.0
Requires-Dist: envyaml>=1.10.211231
Requires-Dist: eumdac>=3.0.0
Requires-Dist: geojson-pydantic>=2.1.0
Requires-Dist: h5netcdf>=1.7.3
Requires-Dist: h5py>=3.15.1
Requires-Dist: netcdf4>=1.7.2
Requires-Dist: odc-stac>=0.4.0
Requires-Dist: pydantic-settings>=2.10.1
Requires-Dist: pydantic>=2.11.9
Requires-Dist: pyhdf>=0.11.6
Requires-Dist: pyproj>=3.7.1
Requires-Dist: pyresample>=1.31.0
Requires-Dist: pyspectral>=0.13.6
Requires-Dist: pystac-client>=0.9.0
Requires-Dist: pystac>=1.14.1
Requires-Dist: rioxarray>=0.19.0
Requires-Dist: satpy>=0.58.0
Requires-Dist: shapely>=2.1.1
Provides-Extra: all
Requires-Dist: mkdocs-material>=9.6.22; extra == 'all'
Requires-Dist: pre-commit>=4.3.0; extra == 'all'
Requires-Dist: pyright>=1.1.406; extra == 'all'
Requires-Dist: pytest-cov>=7.0.0; extra == 'all'
Requires-Dist: pytest-xdist>=3.8.0; extra == 'all'
Requires-Dist: pytest>=8.4.2; extra == 'all'
Requires-Dist: rich>=14.1.0; extra == 'all'
Requires-Dist: ruff>=0.13.2; extra == 'all'
Requires-Dist: typer>=0.19.2; extra == 'all'
Provides-Extra: console
Requires-Dist: rich>=14.1.0; extra == 'console'
Requires-Dist: typer>=0.19.2; extra == 'console'
Provides-Extra: dev
Requires-Dist: mkdocs-material>=9.6.22; extra == 'dev'
Requires-Dist: pre-commit>=4.3.0; extra == 'dev'
Requires-Dist: pyright>=1.1.406; extra == 'dev'
Requires-Dist: ruff>=0.13.2; extra == 'dev'
Provides-Extra: test
Requires-Dist: pytest-cov>=7.0.0; extra == 'test'
Requires-Dist: pytest-xdist>=3.8.0; extra == 'test'
Requires-Dist: pytest>=8.4.2; extra == 'test'
